Workbook

Sheet Estimateur
B2: Estimateur de devis — prestations B2C
B3: Renseignez les cellules jaunes. Particuliers : prix TTC (TVA 20 %).
B5: 1 · Prestation
B6: Prestation | C6: Turnover Airbnb
B7: Typologie | C7: Studio / T1
B8: Prix de base (forfait) | D8: =IF(ISNUMBER($F$8),$F$8,0) -> 55 | F8: =INDEX('Forfaits B2C'!$B$3:$F$6,MATCH($C$6,'Forfaits B2C'!$A$3:$A$6,0),MATCH($C$7,'Forfaits B2C'!$B$2:$F$2,0)) -> 55
B10: 2 · Options
B11: Four en profondeur | C11: Non | D11: =IF($C$11="Oui",Options!$B$5,0) -> 0
B12: Réfrigérateur / congélateur | C12: Non | D12: =IF($C$12="Oui",Options!$B$6,0) -> 0
B13: Vitres intérieures | C13: Non | D13: =IF($C$13="Oui",Options!$B$7,0) -> 0
B14: Intérieur des placards | C14: Non | D14: =IF($C$14="Oui",Options!$B$11,0) -> 0
B15: Réassort consommables | C15: Non | D15: =IF($C$15="Oui",Options!$B$9,0) -> 0
B16: Cave / box | C16: Non | D16: =IF($C$16="Oui",Options!$B$13,0) -> 0
B17: Repassage (heures) | C17: 0 | D17: =$C$17*Options!$B$10 -> 0
B18: Kit linge (nombre de lits) | C18: 0 | D18: =$C$18*Options!$B$8 -> 0
B19: Balcon / terrasse (m²) | C19: 0 | D19: =IF($C$19>0,MAX(20,$C$19*Options!$B$12),0) -> 0
B20: Moquette (m²) | C20: 0 | D20: =IF($C$20>0,MAX(100,$C$20*Options!$B$19),0) -> 0
B21: Sous-total options | D21: =SUM(D11:D20) -> 0
B23: 3 · Majorations & frais
B24: Urgence < 48 h | C24: Non | D24: =IF($C$24="Oui",'Majorations et frais'!$B$5,0) -> 0
B25: Dimanche / jour férié | C25: Non | D25: =IF($C$25="Oui",'Majorations et frais'!$B$6,0) -> 0
B26: Logement non vidé (fin de bail) | C26: Non | D26: =IF($C$26="Oui",'Majorations et frais'!$B$7,0) -> 0
B27: Très encrassé / > 6 mois (grand ménage) | C27: Non | D27: =IF($C$27="Oui",'Majorations et frais'!$B$8,0) -> 0
B28: Total majorations | D28: =D24+D25+D26+D27 -> 0
B29: Étage ≥ 3 sans ascenseur | C29: Non | D29: =IF($C$29="Oui",'Majorations et frais'!$B$9,0) -> 0
B30: Forfait déplacement (€) | C30: 0 | D30: =C30 -> 0
B32: 4 · Total estimé
B33: Sous-total (base + options) | D33: =D8+D21 -> 55
B34: Majorations appliquées | D34: =D33*D28 -> 0
B35: Frais fixes (étage + déplacement) | D35: =D29+D30 -> 0
B36: TOTAL ESTIMÉ | D36: =D33+D34+D35 -> 55
B37: Acompte indicatif (30 %) | D37: =D36*0.3 -> 16.5
B38: Solde à la prestation | D38: =D36-D37 -> 38.5
B40: Mode de vente | C40: =IFERROR(INDEX('Forfaits B2C'!$I$3:$I$6,MATCH($C$6,'Forfaits B2C'!$A$3:$A$6,0)),"") -> Prix fixe en ligne
B41: =IF(ISNUMBER($F$8),"Configuration vendable en ligne à prix fixe.","⚠ Hors forfait → bascule vers devis (voir onglet « Bascule vers devis »).") -> Configuration vendable en ligne à prix fixe.
A43: Majorations appliquées sur (base + options). Acompte 30 % indicatif, à confirmer. Crédit d'impôt 50 % non applicable en l'état (voir « À trancher »).

Sheet Méthode et synthèse
A1: Méthode de décision & synthèse du catalogue
A3: Règle de décision — vendable en ligne à prix fixe SI les 3 conditions sont réunies
A4: 1 · Paramètres déclarables — le client renseigne seul, sans erreur possible, ce qui fait le prix (typologie, surface, logement vide ou non, nombre de lits…).
A5: 2 · Variance maîtrisée — l'écart entre la déclaration et le terrain reste faible ; le risque de vendre à perte est limité et encadrable par les CGV.
A6: 3 · Périmètre fermé — la prestation tient dans une check-list de tâches identique d'une intervention à l'autre (standardisable en forfait).
A7: → Un critère manque : estimation indicative + validation (photos ou audit) avant prix ferme.
A8: → Deux critères manquent, ou contrat récurrent B2B : devis pur après visite.
A10: Synthèse — classement du catalogue
A11: Prestation | B11: Mode de vente | C11: Flux | D11: Raison principale
A12: Turnover Airbnb | B12: Prix fixe en ligne + paiement | C12: B (Stripe) | D12: Typologie déclarable, périmètre fermé, récurrent
A13: Ménage fin de bail / déménagement | B13: Prix fixe en ligne + paiement | C13: B (Stripe) | D13: Standardisable si logement vide
A14: Grand ménage ponctuel (meublé) | B14: Prix fixe en ligne avec question d'état | C14: B (Stripe) | D14: Variance « état » encadrée par coefficient
A15: Vitrerie résidentielle simple | B15: Prix fixe en ligne (plain-pied / intérieur) | C15: B (Stripe) | D15: Bascule devis si hauteur ou vitrine
A16: Fin de chantier | B16: Estimation indicative → prix ferme après photos/audit | C16: A enrichi | D16: Empoussièrement et gravats invérifiables en ligne
A17: Bureaux & locaux pro (régulier) | B17: Devis (avec simulateur de budget indicatif) | C17: A | D17: Fréquence, horaires, cahier des charges, visite
A18: Copropriétés / parties communes | B18: Devis | C18: A | D18: Cahier des charges syndic, fréquences, containers
A19: Commerces / ERP | B19: Devis | C19: A | D19: Contraintes d'exploitation, horaires décalés
A20: Remise en état lourde (insalubre, sinistre, décès) | B20: Devis strict — jamais de chiffre en ligne | C20: A | D20: Variance extrême, risque sanitaire
A21: Textiles (canapé, matelas, moquette) | B21: Prix fixe en option ou mini-grille | C21: B | D21: Le marché vend déjà ces prestations à prix fixe

Sheet Forfaits B2C
A1: Forfaits B2C — prix fixe en ligne (TTC, à valider § Contrôle rentabilité)
A2: Prestation | B2: Studio / T1 | C2: T2 | D2: T3 | E2: T4 | F2: T5 | G2: Au-delà du forfait | H2: Inclus / conditions | I2: Mode de vente
A3: Turnover Airbnb | B3: 55 | C3: 75 | D3: 95 | E3: 120 | F3: À partir de 150 € / devis | G3: Maison / > 90 m² : devis | H3: Ménage de rotation, état d'usage normal | I3: Prix fixe en ligne
A4: Fin de bail / déménagement (logement vide) | B4: 160 | C4: 220 | D4: 290 | E4: 360 | F4: 430 | G4: > 110 m² ou maison : devis | H4: Électroménager + vitres intérieures + placards INCLUS | I4: Prix fixe en ligne
A5: Grand ménage (meublé occupé) | B5: 140 | C5: 190 | D5: 250 | E5: 320 | F5: Devis | G5: T5+ : devis | H5: État courant ; +30 % si très encrassé (ou devis) | I5: Prix fixe + coeff. état
A6: Vitrerie résidentielle simple | B6: 70 | C6: 70 | D6: 95 | E6: 95 | F6: 130 | G6: Hauteur, vitrine, verrière : devis | H6: Plain-pied / intérieur accessible ; minimum 70 € | I6: Prix fixe en ligne
A8: Durées de référence — Turnover Airbnb
A9: Studio / T1 (≤ 35 m²) | B9: ~ 1 h 45
A10: T2 (35–50 m²) | B10: ~ 2 h 15
A11: T3 (50–70 m²) | B11: ~ 2 h 45
A12: T4 (70–90 m²) | B12: ~ 3 h 30
A14: Repères marché 2026 (justification des grilles)
A15: • Airbnb : forfaits rotation studio 30–50 € · T2 50–65 € · T3 60–90 € · >100 m² 80–200 € (~0,8–1,2 €/m²). Coût marché rotation IDF 35–50 € ; le voyageur paie 60–90 € pour un T2 parisien.
A16: • Fin de bail / état des lieux : après déménagement 100–350 € · avant état des lieux 120–400 € · fourchette nationale 160 à 680+ €. Plateformes B2C à partir de ~37,90 €/h. Cuisine et SDB = zones qui déclenchent le plus de retenues sur caution.
A17: • Grand ménage : forfait 150–400 € · ménage à domicile 25–40 €/h.
A18: • Vitrerie : 3–7 €/m² vitré · interventions 50–118 € · 20–40 €/h · travaux en hauteur 7–15 €/m².
A19: • Positionnement : au-dessus du prestataire indépendant (société structurée : encadrement, assurance, contrôle qualité), dans la fourchette de ce que paie déjà le voyageur — neutre pour l'hôte qui refacture.

Sheet Options
A1: Catalogue des options à prix fixe (TTC, à valider)
A3: Suppléments — base de calcul de l'estimateur
A4: Option | B4: Prix | C4: Unité | D4: Compatible avec | E4: Base / justification
A5: Four en profondeur | B5: 35 | C5: € | D5: Airbnb, grand ménage | E5: 30–60 min de travail constaté
A6: Réfrigérateur / congélateur | B6: 25 | C6: € | D6: Airbnb, grand ménage | E6: < 30 min constaté
A7: Vitres intérieures | B7: 20 | C7: € (20–60 selon typologie) | D7: Airbnb, grand ménage | E7: 3–7 €/m² vitré (marché)
A8: Kit linge par lit (location, lavage, livraison) | B8: 18 | C8: €/lit | D8: Airbnb | E8: Coût réel 12–15 €, linge pro 2–4 €/pièce
A9: Réassort consommables | B9: 10 | C9: € | D9: Airbnb | E9: Forfait marché courant
A10: Repassage | B10: 35 | C10: €/h | D10: Airbnb, grand ménage | E10: Taux horaire B2C
A11: Intérieur des placards | B11: 25 | C11: € | D11: Grand ménage | E11: Temps estimé
A12: Balcon / terrasse | B12: 2 | C12: €/m² (min. 20 €) | D12: Fin de bail, grand ménage | E12: Temps estimé
A13: Cave / box | B13: 25 | C13: € | D13: Fin de bail | E13: Temps estimé
A14: Canapé 2 places | B14: 80 | C14: € | D14: Toutes B2C | E14: Grilles fixes concurrentes
A15: Canapé 3 places | B15: 100 | C15: € | D15: Toutes B2C | E15: Grilles fixes concurrentes
A16: Canapé 4 places | B16: 110 | C16: € | D16: Toutes B2C | E16: Grilles fixes concurrentes
... A19: Moquette injection-extraction | B19: 5 | C19: €/m² (min. 100 €) | D19: Fin de bail, bureaux | E19: 100–200 €/intervention (marché)
A21: Textiles (canapé, matelas, fauteuil) : à proposer en OPTION des forfaits plutôt qu'en prestation autonome au lancement — le déplacement seul pour un fauteuil à 50 € est peu rentable.

Sheet Majorations et frais
A1: Majorations & frais standardisables (affichables en ligne)
A3: Taux et frais — base de calcul de l'estimateur
A4: Cas | B4: Valeur | C4: Type | D4: Recommandation / à trancher
A5: Urgence < 48 h | B5: 0.2 | C5: % | D5: Sur le total
A6: Dimanche / jour férié | B6: 0.25 | C6: % | D6: +25 à +50 % — à fixer selon la majoration versée aux prestataires
A7: Logement non vidé (fin de bail) | B7: 0.15 | C7: % | D7: Ou bascule vers devis
A8: Très encrassé / > 6 mois sans entretien (grand ménage) | B8: 0.3 | C8: % | D8: Ou bascule vers devis avec photos
A9: Étage ≥ 3 sans ascenseur | B9: 15 | C9: € | D9: Frais fixe
A10: Zone grande couronne éloignée | B10: 15–30 € | C10: € | D10: Forfait déplacement selon zonage des 8 départements (à définir)
A11: Annulation < 24 h | B11: 0.5 | C11: % du forfait | D11: À inscrire aux CGV

Sheet Estimation chantier
B1: Fin de chantier — estimation indicative (HT, ± 15 %)
A2: Affiché comme fourchette indicative, JAMAIS comme prix ferme. Mention obligatoire : « Prix confirmé après audit gratuit ou envoi de photos ».
B4: Niveau | C4: Taux (€/m² HT) | D4: Descriptif
B5: Rafraîchissement | C5: 4.5 | D5: Peinture seule, sols protégés
B6: Rénovation standard | C6: 7 | D6: Dépoussiérage complet, vitres, traces
B7: Chantier lourd | C7: 11 | D7: Construction neuve, voiles de ciment, gravats
A9: Simulateur (indicatif)
B10: Niveau de chantier | C10: Rénovation standard
B11: Surface (m²) | C11: 60
B12: Taux applicable (€/m² HT) | C12: =IFERROR(VLOOKUP($C$10,$B$5:$C$7,2,0),0) -> 7
B13: Estimation centrale (min. 300 €) | C13: =MAX(300,$C$11*$C$12) -> 420
B14: Fourchette basse (− 15 %) | C14: =ROUND($C$13*0.85,0) -> 357
B15: Fourchette haute (+ 15 %) | C15: =ROUND($C$13*1.15,0) -> 483
A17: Marché 2026 (HT) : IDF 4–15 €/m² · simplifié 2–4 · standard 4–7 · complet 8–12 · ou 3–6 (peu sale) / 6–10 (réno) / 10–15 (lourd, neuf). Accès difficile (étage sans ascenseur, haussmannien, pas de point d'eau) : +10 à 20 %. À l'heure : 30–45 €/h. Minimum d'intervention : 300 € HT.

Sheet Devis B2B et lourd
A1: Prestations sur devis — B2B & remises en état lourdes (HT)
A2: Famille | B2: Détail | C2: Mode de vente | D2: Règle / repère marché
A3: Bureaux & locaux pro (entretien régulier) | B3: Jamais de prix ferme en ligne. Simulateur de budget indicatif possible (surface × fréquence). Position : « à partir de 2 €/m²/mois HT ». | C3: Devis | D3: Standards 1,5–3 €/m²/mois (jusqu'à 4–4,5 en zone tendue) · petits bureaux 3–5 €/m² · grands plateaux 1–2,5 €/m² · 20–35 €/h (pointes 40–45). TPE 50–150 m², 2–3 passages/sem : 300–650 €/mois. IDF +15–25 %.
A4: Copropriétés / parties communes | B4: Cahier des charges syndic, fréquences imposées, containers : visite systématique. Page prestation + formulaire d'audit gratuit. | C4: Devis | D4: Aucun chiffre en ligne.
A5: Commerces / ERP | B5: Contraintes d'exploitation, horaires décalés (avant 8 h / après 19 h). | C5: Devis | D5: Aucun chiffre en ligne.
A6: Remise en état lourde (insalubrité, sinistre, après décès) | B6: Variance extrême, EPI, évacuation de déchets, parfois coordination assurance. Formulaire dédié + visite sous 48 h. | C6: Devis strict | D6: Aucun chiffre en ligne, même indicatif : un montant affiché crée un ancrage intenable.
A8: Simulateur de budget indicatif — bureaux (aimant à leads)
A9: Surface (m²) | C9: 100
A10: Budget mensuel estimé — bas (≈ 1,5 €/m²/mois HT) | C10: =ROUND($C$9*1.5,0) -> 150
A11: Budget mensuel estimé — haut (≈ 3 €/m²/mois HT) | C11: =ROUND($C$9*3,0) -> 300
A13: Indicatif uniquement — devis ferme après audit gratuit. Affiche une fourchette pour rassurer et qualifier le prospect avant la visite.

Sheet Bascule vers devis
A1: Garde-fous du tunnel — bascule automatique vers devis
A3: Le tunnel doit rétrograder proprement vers le Flux A sans perdre le lead — message type : « Votre demande mérite une étude personnalisée : audit gratuit » — dès que l'un de ces cas est rencontré :
B5: • Surface > 110–120 m² (B2C) ou typologie « maison ».
B6: • État déclaré « très dégradé » ou « plus de 6 mois sans entretien » (grand ménage).
B7: • Logement non vidé sur la fin de bail (au choix : +15 % ou devis).
B8: • Vitres en hauteur, vitrine, verrière.
B9: • Toute demande B2B récurrente (bureaux, copropriété, commerce).
B10: • Mots-clés sensibles dans le champ libre : sinistre, insalubre, décès, gravats.
A12: Rappel technique (cohérent avec les règles Stripe)
A13: Les montants affichés par le tunnel sont indicatifs côté navigateur. Le prix encaissé doit TOUJOURS être recalculé côté serveur à partir de la grille KC_CFG avant la création de la session Checkout.

Sheet Contrôle rentabilité
B1: Contrôle de rentabilité — à passer avant toute mise en production
A2: Aucun forfait ne passe en production sans vérifier : Forfait ≥ (heures × coût horaire chargé) + déplacement + consommables/linge + marge cible (≥ 25–30 %). Seuls les coûts réels de Tatiana valident chaque montant.
A4: Saisie (cellules jaunes)
B5: Heures estimées | C5: 2.5
B6: Coût horaire chargé du prestataire (€/h) | C6: 18
B7: Déplacement (€) | C7: 10
B8: Consommables / linge (€) | C8: 5
B9: Marge cible (%) | C9: 0.3
B10: Forfait envisagé (€) | C10: 95
A12: Résultat
B13: Coût direct | C13: =$C$5*$C$6+$C$7+$C$8 -> 60
B14: Forfait plancher (marge sur prix de vente) | C14: =ROUND($C$13/(1-$C$9),0) -> 86
B15: Marge réalisée sur le forfait envisagé (€) | C15: =$C$10-$C$13 -> 35
B16: Marge réalisée (%) | C16: =IFERROR(($C$10-$C$13)/$C$10,0) -> 0.36842105
B17: Verdict | C17: =IF($C$10>=$C$14,"✓ Rentable (marge ≥ cible)","✗ Insuffisant : relever le prix ou réduire les coûts") -> ✓ Rentable (marge ≥ cible)
A19: « Marge sur prix de vente » : plancher = coût direct ÷ (1 − marge cible). Une marge de 30 % signifie que le coût représente 70 % du prix.

Sheet À trancher (Tatiana)
A1: Points que Tatiana doit trancher
B3: 1 · Validation ligne à ligne des grilles (§ Forfaits, Options, Majorations) après passage dans le contrôle de rentabilité.
B4: 2 · TTC / HT : afficher TTC pour les particuliers (TVA 20 %), HT pour les pros (fin de chantier, bureaux). Le tunnel doit l'afficher sans ambiguïté.
B5: 3 · Crédit d'impôt 50 % : les concurrents B2C communiquent des prix « après crédit d'impôt » (≈ moitié prix). Kayli Clinn (NAF 81.21Z) ne peut pas le proposer sans déclaration/agrément Services à la Personne — dispositif imposant une activité exclusive incompatible avec le B2B. À étudier avec l'expert-comptable. En attendant : positionnement sur l'assurance, l'encadrement et la garantie de résultat, pas sur le prix horaire facial.
B6: 4 · Minimum d'intervention global B2C (suggestion : 70–80 €).
B7: 5 · Zonage déplacement sur les 8 départements (Paris / petite couronne incluse, grande couronne avec forfait).
B8: 6 · Inclusions du forfait fin de bail : la recommandation « tout inclus » (four, frigo, vitres intérieures, placards) est un choix commercial. L'alternative « base + options » est possible mais expose à de mauvais avis si le client découvre que l'attendu de l'état des lieux n'était pas inclus.

Sheet Sources et légende
A1: Légende & sources
A3: Prix fixe en ligne | B3: Vendable à prix fixe + paiement immédiat (Flux B, Stripe).
A4: Estimation indicative | B4: Fourchette affichée (jamais ferme), prix confirmé après photos/audit (Flux A enrichi).
A5: Devis | B5: Pas de prix ferme en ligne ; simulateur de budget indicatif possible ; visite/audit (Flux A).
A6: Devis strict | B6: Aucun chiffre en ligne, même indicatif (variance extrême, risque sanitaire).
A8: Repères : prix TTC (particuliers, TVA 20 %) · prix HT (pros : fin de chantier, bureaux)
A10: Sources marché 2025–2026
A11: • Travaux.com — Tarifs entreprise de nettoyage 2026 (taux horaires, vitres 3–7 €/m², grand ménage 150–400 €, forfaits déménagement/état des lieux, moquette 100–200 €).
A12: • Obat — Tarif nettoyage au m² 2026 (fourchette globale 2–30 €/m²).
A13: • IDcleaning — Fin de bail (forfaits 160–680 €) ; Yoojo — ménage état des lieux (durées, zones critiques cuisine/SDB).
A14: • Companeo 2026 — Fin de chantier 2–12 €/m² par niveau ; nettoyage d'entreprise au m² par taille de site.
A15: • France Clean 2026 — Nettoyage professionnel au m² (bureaux 1,5–3 €/m²/mois, fin de chantier 4–10 € HT/m², IDF +15–25 %).
A16: • Nettoyage-entreprise-paris.com 2026 — Fin de chantier Paris/IDF 4–15 € HT/m², majorations accès +10–20 %.
A17: • L'Océane 2026 — Fin de chantier 3–6 / 6–10 / 10–15 €/m² ; locaux pro 1,5–4 €/m², budgets TPE IDF 300–650 €/mois.
A18: • Leazly, ImmobilierJuridique 2026, Rentaplus 2026 — Forfaits Airbnb par typologie, coût rotation IDF 35–50 €, frais voyageur T2 parisien 60–90 €, linge pro 2–4 €/pièce, kit linge+consommables 12–15 €.
A19: • DNA Propreté 2026, Vitrissimo — Vitres : 0,5–4 €/m², 20–40 €/h, interventions 50–118 €.
A20: • Fée du Propre — Grille fixe textiles (fauteuil 50 €, canapé 2/3/4 pl. 80/100/110 €, matelas 70–100 €).
A22: Document de travail interne. Les montants « recommandés » sont des hypothèses construites sur le marché 2026 ; ils n'engagent Kayli Clinn qu'après validation par la propriétaire et passage dans la formule de rentabilité.
